dummypypi2/__init__.py
dummypypi2/utils.py
dummypypi2-0.1.9.dist-info/METADATA
dummypypi2-0.1.9.dist-info/WHEEL
dummypypi2-0.1.9.dist-info/top_level.txt
dummypypi2-0.1.9.dist-info/RECORD
