Metadata-Version: 2.1
Name: dummypypi2
Version: 0.1.9
Summary: To be deleted later
Author: Bart Wolleswinkel
Author-email: b.wolleswinkel@tudelft.nl
Keywords: python,dummy,github,pypi,test
Classifier: Development Status :: 1 - Planning
Classifier: Intended Audience :: Developers
Classifier: Programming Language :: Python :: 3
Classifier: Operating System :: Unix
Classifier: Operating System :: MacOS :: MacOS X
Classifier: Operating System :: Microsoft :: Windows
Requires-Dist: numpy
